{"packages/cupertino_icons/assets/CupertinoIcons.ttf":["packages/cupertino_icons/assets/CupertinoIcons.ttf"],"lib/assets/follower2.jpg":["lib/assets/follower2.jpg"],"lib/assets/follower3.jpeg":["lib/assets/follower3.jpeg"],"lib/assets/my_profile.jpg":["lib/assets/my_profile.jpg"],"lib/assets/photo4.jpg":["lib/assets/photo4.jpg"],"lib/assets/photo5.jpg":["lib/assets/photo5.jpg"],"lib/assets/photo_1.jpeg":["lib/assets/photo_1.jpeg"],"lib/assets/post2.jpg":["lib/assets/post2.jpg"],"lib/assets/profile3.png":["lib/assets/profile3.png"],"lib/assets/profile4.png":["lib/assets/profile4.png"],"lib/assets/profile6.jpg":["lib/assets/profile6.jpg"],"lib/assets/their_profile.jpeg":["lib/assets/their_profile.jpeg"]}